{"name":"一寸","width_px":295,"height_px":413,"width_mm":25,"height_mm":35,"category_id":"1","discription":"教师资格证、简历、会计职称考试、健康证等"}
{"name":"小一寸","width_px":260,"height_px":378,"width_mm":22,"height_mm":32,"category_id":"1","discription":"驾驶证、驾照、英语AB级等"}
{"name":"大一寸","width_px":390,"height_px":567,"width_mm":33,"height_mm":48,"category_id":"1","discription":"计算机等级、中国护照、英语四六级考试等"}
{"name":"二寸","width_px":413,"height_px":579,"width_mm":35,"height_mm":49,"category_id":"1","discription":"养老护理员、医疗、职业药师资格证等"}
{"name":"小二寸","width_px":413,"height_px":531,"width_mm":35,"height_mm":45,"category_id":"1","discription":"国考、国家公务员、护士资格证考试、主管护师等"}
{"name":"大二寸","width_px":413,"height_px":626,"width_mm":35,"height_mm":53,"category_id":"1","discription":"签证、港澳通行证等"}
{"name":"教师资格证","width_px":295,"height_px":413,"width_mm":25,"height_mm":35,"category_id":"2","discription":"教师资格证考试专用"}
{"name":"护士资格证","width_px":413,"height_px":531,"width_mm":35,"height_mm":45,"category_id":"2","discription":"护士资格证考试专用"}
{"name":"会计职称","width_px":295,"height_px":413,"width_mm":25,"height_mm":35,"category_id":"2","discription":"会计职称考试专用"}
{"name":"医师资格证","width_px":413,"height_px":626,"width_mm":35,"height_mm":53,"category_id":"2","discription":"医师资格证考试专用"}
{"name":"药师资格证","width_px":413,"height_px":579,"width_mm":35,"height_mm":49,"category_id":"2","discription":"药师资格证考试专用"}
{"name":"建造师","width_px":295,"height_px":413,"width_mm":25,"height_mm":35,"category_id":"2","discription":"建造师考试专用"}
{"name":"国家公务员","width_px":413,"height_px":531,"width_mm":35,"height_mm":45,"category_id":"3","discription":"国家公务员考试专用"}
{"name":"事业单位","width_px":413,"height_px":531,"width_mm":35,"height_mm":45,"category_id":"3","discription":"事业单位考试专用"}
{"name":"省考公务员","width_px":413,"height_px":531,"width_mm":35,"height_mm":45,"category_id":"3","discription":"省考公务员考试专用"}
{"name":"英语四六级","width_px":390,"height_px":567,"width_mm":33,"height_mm":48,"category_id":"4","discription":"英语四六级考试专用"}
{"name":"计算机等级","width_px":390,"height_px":567,"width_mm":33,"height_mm":48,"category_id":"4","discription":"计算机等级考试专用"}
{"name":"研究生考试","width_px":390,"height_px":567,"width_mm":33,"height_mm":48,"category_id":"4","discription":"研究生考试专用"}
{"name":"托福雅思","width_px":390,"height_px":567,"width_mm":33,"height_mm":48,"category_id":"4","discription":"托福雅思考试专用"}
{"name":"普通话考试","width_px":390,"height_px":567,"width_mm":33,"height_mm":48,"category_id":"4","discription":"普通话考试专用"}
